notification_typing/IndicatorCondition.py
notification_typing/NotificationCondition.py
notification_typing/NotificationConditionEvaluator.py
notification_typing/NotificationConditionType.py
notification_typing/NotificationType.py
notification_typing/PriceCondition.py
notification_typing/SignalCondition.py
notification_typing/Subscription.py
notification_typing/__init__.py
notification_typing-0.3.2.dist-info/METADATA
notification_typing-0.3.2.dist-info/WHEEL
notification_typing-0.3.2.dist-info/top_level.txt
notification_typing-0.3.2.dist-info/RECORD
