Metadata-Version: 2.2
Name: notification-typing
Version: 0.3.2
Summary: A shared typing module for notification services.
Author-email: Tommy Pang <tommypang04@gmail.com>
License: MIT
Requires-Python: >=3.10
